{
  "kind": "singleType",
  "collectionName": "about_uses",
  "info": {
    "singularName": "about-us",
    "pluralName": "about-uses",
    "displayName": "AboutUs",
    "description": ""
  },
  "options": {
    "draftAndPublish": true
  },
  "pluginOptions": {},
  "attributes": {
    "banner": {
      "type": "component",
      "repeatable": true,
      "component": "system-kit.banner-without-button-kit"
    },
    "theTeamSection": {
      "type": "component",
      "repeatable": true,
      "component": "system-kit.team-block"
    },
    "firstFeedbackSection": {
      "type": "component",
      "repeatable": true,
      "component": "system-kit.image-with-description-kit"
    },
    "secondFeedbackSection": {
      "type": "component",
      "repeatable": true,
      "component": "system-kit.image-with-description-kit"
    },
    "thirdFeedbackSection": {
      "type": "component",
      "repeatable": true,
      "component": "system-kit.image-with-description-kit"
    },
    "meta": {
      "type": "relation",
      "relation": "oneToOne",
      "target": "api::meta.meta"
    }
  }
}
